kelpie_personal_trainer/__init__.py
kelpie_personal_trainer/accuracy_and_counter.py
kelpie_personal_trainer/body_type.py
kelpie_personal_trainer/models/knnpickle_file.pickle
kelpie_personal_trainer/models/knnpickle_file_woman.pickle
kelpie_personal_trainer/models/lstm_model_pushup.h5
kelpie_personal_trainer/models/lstm_model_situp.h5
kelpie_personal_trainer/models/lstm_model_squat.h5
kelpie_personal_trainer-0.2.18.dist-info/METADATA
kelpie_personal_trainer-0.2.18.dist-info/WHEEL
kelpie_personal_trainer-0.2.18.dist-info/top_level.txt
kelpie_personal_trainer-0.2.18.dist-info/RECORD
