Metadata-Version: 2.1
Name: kelpie-personal-trainer
Version: 0.2.18
Summary: Personal Trainer Library
Home-page: UNKNOWN
Author: Ariel
Author-email: <arillesmana2001@gmail.com>
License: UNKNOWN
Keywords: python
Platform: UNKNOWN
Classifier: Development Status :: 1 - Planning
Classifier: Intended Audience :: Developers
Classifier: Programming Language :: Python :: 3
Classifier: Operating System :: Unix
Classifier: Operating System :: MacOS :: MacOS X
Classifier: Operating System :: Microsoft :: Windows
Requires-Dist: scikit-learn
Requires-Dist: pandas
Requires-Dist: opencv-python
Requires-Dist: mediapipe
Requires-Dist: numpy
Requires-Dist: tensorflow
Requires-Dist: keras
Requires-Dist: matplotlib
